[
  {
    "id": 1,
    "type": "incolor",
    "name": "Incolor",
    "description": "Lente simples, sem nenhum tratamento",
    "tip": "Indicada para uso de oculos simples e baixo orçamento",
    "icon": "/images/anti.png"
  },
  {
    "id": 2,
    "type": "anti-reflexo",
    "name": "Anti Reflexo",
    "description": "Lentes com proteção de anti reflexo, indicada para quem usa mais o óculos",
    "tip": "Indicada para usuários ... ",
    "icon": "/images/glasses2.png"
  },
  {
    "id": 3,
    "type": "antiblue",
    "name": "Anti Blue",
    "description": "Lentes anti blue",
    "tip": "Indicada para clientes... ",
    "icon": "/images/glasses2.png"
  },
  {
    "id": 4,
    "type": "foto",
    "name": "Foto",
    "description": "Lentes utilizadas para quem está no sol",
    "tip": "Indicada para uso de ...",
    "icon": "/images/glasses2.png"
  },
  {
    "id": 5,
    "type": "fotoBlue",
    "name": "Foto Blue",
    "description": "Lentes para uso de foto",
    "tip": "",
    "icon": "/images/safety-glasses.png"
  },
  {
    "id": 6,
    "type": "solar",
    "name": "Solar",
    "description": "Lentes indicadas para sol",
    "tip": "",
    "icon": "/images/solar.png"
  },
  {
    "id": 7,
    "type": "polarizada",
    "name": "Polarizada",
    "description": "Lentes solares",
    "tip": "",
    "icon": "/images/polarizada.png"
  },
  {
    "id": 8,
    "type": "multiFocal",
    "name": "Multi Focal Pronto",
    "description": "Lentes com Grau para perto e para longe",
    "tip": "",
    "icon": "/images/glasses.png"
  }
]
